stealth25519/__init__.py
stealth25519/address.py
stealth25519/ed25519.py
stealth25519/generator.py
stealth25519/key.py
stealth25519/signer.py
stealth25519/verifier.py
stealth25519-1.0.9.dist-info/LICENSE
stealth25519-1.0.9.dist-info/METADATA
stealth25519-1.0.9.dist-info/WHEEL
stealth25519-1.0.9.dist-info/top_level.txt
stealth25519-1.0.9.dist-info/RECORD
